{"npi":"1003022997","name":"Yanina Krayevsky","credentials":"D.D.S.","entityCode":"I","city":"Merrick","state":"NY","zip5":"11566","specialty":"Dentist","claims":21,"fills30":21,"cost":234,"daySupply":346,"benes":16,"costPerBene":15,"costPerClaim":11,"brandClaims":0,"brandCost":0,"genericClaims":15,"genericCost":128,"brandPct":0,"opioidClaims":0,"opioidCost":0,"opioidBenes":0,"opioidRate":0,"opioidLAClaims":0,"opioidLARate":0,"antibioticClaims":0,"antipsychGE65Claims":0,"avgAge":71.1,"femalePct":null,"avgRiskScore":1.7,"riskScore":0,"riskFlags":[],"riskLevel":"low","isExcluded":false,"exclusionInfo":null}