{"npi":"1003103920","name":"Michael Davis","credentials":"D.D.S.","entityCode":"I","city":"\"San Antonio\"","state":"TX","zip5":"78237","specialty":"US","claims":0,"fills30":367,"cost":376,"daySupply":1873.62,"benes":3249,"costPerBene":0,"costPerClaim":0,"brandClaims":0,"brandCost":0,"genericClaims":0,"genericCost":338,"brandPct":0,"opioidClaims":821.62,"opioidCost":72,"opioidBenes":176,"opioidRate":61,"opioidLAClaims":19.61852861,"opioidLARate":0,"antibioticClaims":0,"antipsychGE65Claims":0,"avgAge":0,"femalePct":0,"avgRiskScore":72,"riskScore":0,"riskFlags":[],"riskLevel":"low","isExcluded":false,"exclusionInfo":null}