{"npi":"1003137852","name":"Quincy Scarborough","credentials":"M.D.","entityCode":"I","city":"Middleburg","state":"FL","zip5":"32068","specialty":"US","claims":0,"fills30":5020,"cost":12161,"daySupply":429913.54,"benes":358376,"costPerBene":0,"costPerClaim":0,"brandClaims":0,"brandCost":594,"genericClaims":0,"genericCost":4406,"brandPct":0,"opioidClaims":400263.38,"opioidCost":23,"opioidBenes":395,"opioidRate":0,"opioidLAClaims":0.4581673307,"opioidLARate":0,"antibioticClaims":0,"antipsychGE65Claims":0,"avgAge":0,"femalePct":7.2,"avgRiskScore":292,"riskScore":0,"riskFlags":[],"riskLevel":"low","isExcluded":false,"exclusionInfo":null}