{"npi":"1003094251","name":"Meredith Mcamis","credentials":"PA-C","entityCode":"I","city":"Springfield","state":"MO","zip5":"65807","specialty":"Physician Assistant","claims":274,"fills30":291.8,"cost":3458,"daySupply":3688,"benes":159,"costPerBene":22,"costPerClaim":13,"brandClaims":0,"brandCost":0,"genericClaims":266,"genericCost":2930,"brandPct":0,"opioidClaims":139,"opioidCost":899,"opioidBenes":136,"opioidRate":50.7,"opioidLAClaims":0,"opioidLARate":0,"antibioticClaims":0,"antipsychGE65Claims":0,"avgAge":68.4,"femalePct":65.4,"avgRiskScore":1.32,"riskScore":26,"riskFlags":["high_opioid_vs_peers","95th_pctile_opioid","very_low_drug_diversity"],"riskLevel":"moderate","isExcluded":false,"exclusionInfo":null,"topDrugs":[{"drug":"Hydrocodone/Acetaminophen","brand":"Hydrocodone-Acetaminophen","claims":134,"cost":890},{"drug":"Ondansetron","brand":"Ondansetron Odt","claims":48,"cost":555},{"drug":"Nifedipine","brand":"Nifedipine Er","claims":20,"cost":276},{"drug":"Pantoprazole Sodium","brand":"Pantoprazole Sodium","claims":11,"cost":174}],"zScores":{"opioid":2.5,"cost":-0.3,"brand":-0.58,"opioidLA":-0.19},"anomalyScore":26,"peerComparison":{"opioidVsPeer":452,"costVsPeer":-97,"brandVsPeer":null},"specialtyAvg":{"opioidRate":9.19,"costPerBene":719,"brandPct":6.65,"providers":109535},"drugDiversity":4,"prescribesOpioid":true,"prescribesBenzo":false,"opioidBenzoCombination":false,"iraDrugCost":0,"glp1Cost":0,"riskComponents":{"opioidPeer":10,"opioidPop":10,"costOutlier":0,"brandPref":0,"opioidLA":0,"antipsych":0,"drugCombo":0,"leie":0,"lowDiversity":6,"frequentFills":0},"claimsPerBene":1.72}