{"npi":"1023045523","name":"Samir Hadeed","credentials":"M.D.","entityCode":"I","city":"Johnstown","state":"PA","zip5":"15904","specialty":"Cardiology","claims":17884,"fills30":40301.89,"cost":3833613,"daySupply":1199922,"benes":2226,"costPerBene":1722,"costPerClaim":214,"brandClaims":4261,"brandCost":3522174,"genericClaims":13623,"genericCost":311439,"brandPct":23.8,"opioidClaims":0,"opioidCost":0,"opioidBenes":0,"opioidRate":0,"opioidLAClaims":0,"opioidLARate":0,"antibioticClaims":65,"antipsychGE65Claims":0,"avgAge":74,"femalePct":50.2,"avgRiskScore":1.4,"riskScore":0,"riskFlags":[],"riskLevel":"low","isExcluded":false,"exclusionInfo":null,"topDrugs":[{"drug":"Apixaban","brand":"Eliquis","claims":1272,"cost":1090708},{"drug":"Rivaroxaban","brand":"Xarelto","claims":962,"cost":893643},{"drug":"Sacubitril/Valsartan","brand":"Entresto","claims":856,"cost":847107},{"drug":"Empagliflozin","brand":"Jardiance","claims":254,"cost":259379},{"drug":"Evolocumab","brand":"Repatha Sureclick","claims":182,"cost":142267},{"drug":"Dapagliflozin Propanediol","brand":"Farxiga","claims":113,"cost":107576},{"drug":"Pitavastatin Calcium","brand":"Livalo","claims":63,"cost":39415},{"drug":"Clopidogrel Bisulfate","brand":"Clopidogrel","claims":2243,"cost":38927},{"drug":"Metoprolol Succinate","brand":"Metoprolol Succinate","claims":1807,"cost":35756},{"drug":"Ticagrelor","brand":"Brilinta","claims":37,"cost":35249},{"drug":"Rosuvastatin Calcium","brand":"Rosuvastatin Calcium","claims":997,"cost":29381},{"drug":"Atorvastatin Calcium","brand":"Atorvastatin Calcium","claims":1373,"cost":27222},{"drug":"Bempedoic Acid/Ezetimibe","brand":"Nexlizet","claims":32,"cost":26374},{"drug":"Icosapent Ethyl","brand":"Icosapent Ethyl","claims":63,"cost":24323},{"drug":"Evolocumab","brand":"Repatha Syringe","claims":29,"cost":24014}],"zScores":{"opioid":-0.08,"cost":0.06,"brand":1.09,"opioidLA":-0.03},"anomalyScore":0,"peerComparison":{"opioidVsPeer":null,"costVsPeer":13,"brandVsPeer":75},"specialtyAvg":{"opioidRate":0.09,"costPerBene":1524,"brandPct":13.65,"providers":18720},"drugDiversity":53,"prescribesOpioid":false,"prescribesBenzo":false,"opioidBenzoCombination":false,"iraDrugCost":3198413,"glp1Cost":0,"riskComponents":{"opioidPeer":0,"opioidPop":0,"costOutlier":0,"brandPref":0,"opioidLA":0,"antipsych":0,"drugCombo":0,"leie":0,"lowDiversity":0,"frequentFills":0},"claimsPerBene":8.03}