{"npi":"1023147675","name":"Robert Buckingham","credentials":"MD","entityCode":"I","city":"Ojai","state":"CA","zip5":"93023","specialty":"Internal Medicine","claims":13406,"fills30":16486.91,"cost":1212693,"daySupply":405081,"benes":351,"costPerBene":3455,"costPerClaim":90,"brandClaims":2099,"brandCost":901360,"genericClaims":11257,"genericCost":309628,"brandPct":15.7,"opioidClaims":768,"opioidCost":30505,"opioidBenes":5.728778159,"opioidRate":5.728778159,"opioidLAClaims":122,"opioidLARate":15.9,"antibioticClaims":287,"antipsychGE65Claims":270,"avgAge":75.8,"femalePct":53.6,"avgRiskScore":2.36,"riskScore":30,"riskFlags":["high_la_opioid","high_antipsych_elderly"],"riskLevel":"elevated","isExcluded":false,"exclusionInfo":null}