{"npi":"1033208145","name":"James Knapp","credentials":"M.D.","entityCode":"I","city":"Turlock","state":"CA","zip5":"95382","specialty":"Family Practice","claims":13729,"fills30":31965.12,"cost":1257302,"daySupply":944371,"benes":906,"costPerBene":1388,"costPerClaim":92,"brandClaims":1375,"brandCost":972257,"genericClaims":12271,"genericCost":281309,"brandPct":10.1,"opioidClaims":319,"opioidCost":10502,"opioidBenes":2.3235486925,"opioidRate":2.3235486925,"opioidLAClaims":12,"opioidLARate":3.8,"antibioticClaims":141,"antipsychGE65Claims":42,"avgAge":74.7,"femalePct":51.4,"avgRiskScore":1.01,"riskScore":15,"riskFlags":["elevated_antipsych_elderly","opioid_benzo_coprescriber"],"riskLevel":"moderate","isExcluded":false,"exclusionInfo":null,"topDrugs":[{"drug":"Empagliflozin","brand":"Jardiance","claims":206,"cost":210773},{"drug":"Dulaglutide","brand":"Trulicity","claims":95,"cost":129030},{"drug":"Rivaroxaban","brand":"Xarelto","claims":100,"cost":94106},{"drug":"Apixaban","brand":"Eliquis","claims":55,"cost":56673},{"drug":"Dapagliflozin Propanediol","brand":"Farxiga","claims":36,"cost":45639},{"drug":"Semaglutide","brand":"Rybelsus","claims":29,"cost":40105},{"drug":"Sitagliptin Phosphate","brand":"Januvia","claims":27,"cost":39806},{"drug":"Tirzepatide","brand":"Mounjaro","claims":21,"cost":32726},{"drug":"Insulin Glargine,hum.Rec.Anlog","brand":"Lantus Solostar","claims":43,"cost":29849},{"drug":"Insulin Glargine,hum.Rec.Anlog","brand":"Lantus","claims":54,"cost":27917},{"drug":"Fluticasone/Umeclidin/Vilanter","brand":"Trelegy Ellipta","claims":30,"cost":25250},{"drug":"Atorvastatin Calcium","brand":"Atorvastatin Calcium","claims":1273,"cost":23957},{"drug":"Sitagliptin Phos/Metformin Hcl","brand":"Janumet","claims":19,"cost":23291},{"drug":"Fluticasone/Vilanterol","brand":"Breo Ellipta","claims":43,"cost":17732},{"drug":"Budesonide/Formoterol Fumarate","brand":"Symbicort","claims":32,"cost":17366}],"zScores":{"opioid":-0.06,"cost":0.19,"brand":0.13,"opioidLA":0.16},"anomalyScore":15,"peerComparison":{"opioidVsPeer":-10,"costVsPeer":30,"brandVsPeer":12},"specialtyAvg":{"opioidRate":2.58,"costPerBene":1068,"brandPct":9,"providers":106889},"drugDiversity":145,"prescribesOpioid":true,"prescribesBenzo":true,"opioidBenzoCombination":true,"iraDrugCost":450031,"glp1Cost":201861,"riskComponents":{"opioidPeer":0,"opioidPop":0,"costOutlier":0,"brandPref":0,"opioidLA":0,"antipsych":5,"drugCombo":8,"leie":0,"lowDiversity":0,"frequentFills":0},"claimsPerBene":15.15}