{"npi":"1043219876","name":"Robert Wang","credentials":"","entityCode":"I","city":"Mountain Lakes","state":"NJ","zip5":"7046","specialty":"Interventional Cardiology","claims":13287,"fills30":35400.76,"cost":2079661,"daySupply":1057005,"benes":1441,"costPerBene":1443,"costPerClaim":157,"brandClaims":0,"brandCost":0,"genericClaims":11695,"genericCost":283281,"brandPct":0,"opioidClaims":0,"opioidCost":0,"opioidBenes":0,"opioidRate":0,"opioidLAClaims":0,"opioidLARate":0,"antibioticClaims":29,"antipsychGE65Claims":0,"avgAge":77.2,"femalePct":48.4,"avgRiskScore":1.21,"riskScore":0,"riskFlags":[],"riskLevel":"low","isExcluded":false,"exclusionInfo":null}