{"npi":"1043384654","name":"Kolawole Odulaja","credentials":"MD","entityCode":"I","city":"San Antonio","state":"TX","zip5":"78258","specialty":"Internal Medicine","claims":22167,"fills30":22215.37,"cost":1649733,"daySupply":534440,"benes":1054,"costPerBene":1565,"costPerClaim":74,"brandClaims":3979,"brandCost":1095334,"genericClaims":18065,"genericCost":544488,"brandPct":18.1,"opioidClaims":0,"opioidCost":0,"opioidBenes":0,"opioidRate":0,"opioidLAClaims":0,"opioidLARate":0,"antibioticClaims":504,"antipsychGE65Claims":656,"avgAge":76.3,"femalePct":57.2,"avgRiskScore":3.34,"riskScore":15,"riskFlags":["high_antipsych_elderly"],"riskLevel":"moderate","isExcluded":false,"exclusionInfo":null,"topDrugs":[{"drug":"Apixaban","brand":"Eliquis","claims":984,"cost":284943},{"drug":"Paliperidone Palmitate","brand":"Invega Sustenna","claims":14,"cost":44733},{"drug":"Rivaroxaban","brand":"Xarelto","claims":152,"cost":43893},{"drug":"Epoetin Alfa","brand":"Procrit","claims":66,"cost":42808},{"drug":"Sitagliptin Phosphate","brand":"Januvia","claims":141,"cost":39193},{"drug":"Insulin Glargine,hum.Rec.Anlog","brand":"Lantus","claims":98,"cost":36311},{"drug":"Insulin Glargine,hum.Rec.Anlog","brand":"Lantus Solostar","claims":225,"cost":33482},{"drug":"Collagenase Clostridium Hist.","brand":"Santyl","claims":53,"cost":32780},{"drug":"Rifaximin","brand":"Xifaxan","claims":21,"cost":30376},{"drug":"Sacubitril/Valsartan","brand":"Entresto","claims":62,"cost":25563},{"drug":"Risperidone Microspheres","brand":"Risperdal Consta","claims":19,"cost":23955},{"drug":"Insulin Glargine,hum.Rec.Anlog","brand":"Basaglar Kwikpen U-100","claims":193,"cost":22166},{"drug":"Sevelamer Carbonate","brand":"Sevelamer Carbonate","claims":38,"cost":21388},{"drug":"Divalproex Sodium","brand":"Divalproex Sodium","claims":301,"cost":18494},{"drug":"Potassium Chloride","brand":"Potassium Chloride","claims":435,"cost":17241}]}