{"npi":"1053744524","name":"Christopher Smith","credentials":"P.A.","entityCode":"I","city":"Corvallis","state":"OR","zip5":"97330","specialty":"Physician Assistant","claims":7136,"fills30":7455.47,"cost":414874,"daySupply":206369,"benes":539,"costPerBene":770,"costPerClaim":58,"brandClaims":342,"brandCost":220575,"genericClaims":6794,"genericCost":194299,"brandPct":4.8,"opioidClaims":4154,"opioidCost":257160,"opioidBenes":378,"opioidRate":58.211883408,"opioidLAClaims":935,"opioidLARate":22.5,"antibioticClaims":0,"antipsychGE65Claims":0,"avgAge":68.3,"femalePct":71.6,"avgRiskScore":1.4,"riskScore":41,"riskFlags":["high_opioid_vs_peers","95th_pctile_opioid","high_la_opioid_vs_peers","opioid_benzo_coprescriber"],"riskLevel":"elevated","isExcluded":false,"exclusionInfo":null,"topDrugs":[{"drug":"Hydrocodone/Acetaminophen","brand":"Hydrocodone-Acetaminophen","claims":1182,"cost":39012},{"drug":"Buprenorphine Hcl","brand":"Belbuca","claims":44,"cost":38000},{"drug":"Buprenorphine","brand":"Buprenorphine","claims":103,"cost":36285},{"drug":"Rimegepant Sulfate","brand":"Nurtec Odt","claims":30,"cost":33505},{"drug":"Erenumab-Aooe","brand":"Aimovig Autoinjector","claims":28,"cost":27871},{"drug":"Oxycodone Hcl","brand":"Oxycodone Hcl","claims":974,"cost":23075},{"drug":"Oxycodone Hcl","brand":"Oxycontin","claims":44,"cost":17712},{"drug":"Oxycodone Myristate","brand":"Xtampza Er","claims":30,"cost":15957},{"drug":"Oxycodone Hcl/Acetaminophen","brand":"Oxycodone-Acetaminophen","claims":462,"cost":15876},{"drug":"Gabapentin","brand":"Gabapentin","claims":564,"cost":11689},{"drug":"Morphine Sulfate","brand":"Morphine Sulfate Er","claims":407,"cost":11552},{"drug":"Pregabalin","brand":"Pregabalin","claims":350,"cost":7213},{"drug":"Naloxegol Oxalate","brand":"Movantik","claims":17,"cost":7071},{"drug":"Fentanyl","brand":"Fentanyl","claims":74,"cost":6220},{"drug":"Linaclotide","brand":"Linzess","claims":11,"cost":6190}],"zScores":{"opioid":2.95,"cost":0.02,"brand":-0.16,"opioidLA":4.46},"anomalyScore":41,"peerComparison":{"opioidVsPeer":533,"costVsPeer":7,"brandVsPeer":-28},"specialtyAvg":{"opioidRate":9.19,"costPerBene":719,"brandPct":6.65,"providers":109535},"drugDiversity":51,"prescribesOpioid":true,"prescribesBenzo":true,"opioidBenzoCombination":true,"iraDrugCost":0,"glp1Cost":0,"riskComponents":{"opioidPeer":10,"opioidPop":10,"costOutlier":0,"brandPref":0,"opioidLA":8,"antipsych":0,"drugCombo":8,"leie":0}}