{"npi":"1063078541","name":"Juan Huang","credentials":"AGPCNP","entityCode":"I","city":"Brooklyn","state":"NY","zip5":"11214","specialty":"Nurse Practitioner","claims":12694,"fills30":17070.14,"cost":2061178,"daySupply":494684,"benes":739,"costPerBene":2789,"costPerClaim":162,"brandClaims":2734,"brandCost":1747424,"genericClaims":9669,"genericCost":308073,"brandPct":22,"opioidClaims":0,"opioidCost":0,"opioidBenes":0,"opioidRate":0,"opioidLAClaims":0,"opioidLARate":0,"antibioticClaims":229,"antipsychGE65Claims":27,"avgAge":72.8,"femalePct":51.7,"avgRiskScore":1.08,"riskScore":8,"riskFlags":["elevated_antipsych_elderly"],"riskLevel":"low","isExcluded":false,"exclusionInfo":null}