{"npi":"1083797716","name":"Janet Dabson","credentials":"MD","entityCode":"I","city":"Janesville","state":"WI","zip5":"53546","specialty":"Family Practice","claims":10152,"fills30":23228.64,"cost":940407,"daySupply":673880,"benes":737,"costPerBene":1276,"costPerClaim":93,"brandClaims":1264,"brandCost":753962,"genericClaims":8782,"genericCost":178385,"brandPct":12.6,"opioidClaims":121,"opioidCost":1204,"opioidBenes":1.1918833727,"opioidRate":1.1918833727,"opioidLAClaims":0,"opioidLARate":0,"antibioticClaims":364,"antipsychGE65Claims":42,"avgAge":71.4,"femalePct":70.7,"avgRiskScore":1.18,"riskScore":8,"riskFlags":["elevated_antipsych_elderly"],"riskLevel":"low","isExcluded":false,"exclusionInfo":null}