{"npi":"1093702912","name":"David Carlyle","credentials":"M.D.","entityCode":"I","city":"Ames","state":"IA","zip5":"50010","specialty":"Family Practice","claims":11316,"fills30":23478.89,"cost":1291547,"daySupply":674012,"benes":534,"costPerBene":2419,"costPerClaim":114,"brandClaims":1388,"brandCost":1069162,"genericClaims":9823,"genericCost":204727,"brandPct":12.4,"opioidClaims":402,"opioidCost":7231,"opioidBenes":3.5524920467,"opioidRate":3.5524920467,"opioidLAClaims":97,"opioidLARate":24.1,"antibioticClaims":232,"antipsychGE65Claims":78,"avgAge":75.6,"femalePct":52.1,"avgRiskScore":1.02,"riskScore":25,"riskFlags":["elevated_la_opioid","high_antipsych_elderly","opioid_benzo_coprescriber"],"riskLevel":"moderate","isExcluded":false,"exclusionInfo":null,"topDrugs":[{"drug":"Apixaban","brand":"Eliquis","claims":158,"cost":163560},{"drug":"Deutetrabenazine","brand":"Austedo","claims":24,"cost":114105},{"drug":"Sitagliptin Phosphate","brand":"Januvia","claims":146,"cost":103490},{"drug":"Semaglutide","brand":"Ozempic","claims":49,"cost":63436},{"drug":"Rivaroxaban","brand":"Xarelto","claims":47,"cost":49684},{"drug":"Insulin Aspart","brand":"Novolog Flexpen","claims":27,"cost":46892},{"drug":"Insulin Glargine,hum.Rec.Anlog","brand":"Lantus Solostar","claims":37,"cost":41230},{"drug":"Evolocumab","brand":"Repatha Sureclick","claims":17,"cost":19492},{"drug":"Levetiracetam","brand":"Keppra","claims":12,"cost":14563},{"drug":"Budesonide/Formoterol Fumarate","brand":"Symbicort","claims":23,"cost":13064},{"drug":"Fluticasone/Umeclidin/Vilanter","brand":"Trelegy Ellipta","claims":18,"cost":11526},{"drug":"Estrogens, Conjugated","brand":"Premarin","claims":36,"cost":11397},{"drug":"Estradiol","brand":"Estradiol","claims":92,"cost":9221},{"drug":"Liraglutide","brand":"Victoza 2-Pak","claims":11,"cost":7878},{"drug":"Insulin Glargine,hum.Rec.Anlog","brand":"Basaglar Kwikpen U-100","claims":15,"cost":7842}],"zScores":{"opioid":0.22,"cost":0.8,"brand":0.41,"opioidLA":2.93},"anomalyScore":25,"peerComparison":{"opioidVsPeer":38,"costVsPeer":127,"brandVsPeer":38},"specialtyAvg":{"opioidRate":2.58,"costPerBene":1068,"brandPct":9,"providers":106889},"drugDiversity":134,"prescribesOpioid":true,"prescribesBenzo":true,"opioidBenzoCombination":true,"iraDrugCost":363625,"glp1Cost":71314,"riskComponents":{"opioidPeer":0,"opioidPop":0,"costOutlier":0,"brandPref":0,"opioidLA":4,"antipsych":10,"drugCombo":8,"leie":0}}