{"npi":"1104093996","name":"Michael Francis","credentials":"D.O.","entityCode":"I","city":"Logan","state":"UT","zip5":"84341","specialty":"Internal Medicine","claims":9892,"fills30":21754.34,"cost":899235,"daySupply":636828,"benes":698,"costPerBene":1288,"costPerClaim":91,"brandClaims":1130,"brandCost":711803,"genericClaims":8686,"genericCost":183718,"brandPct":11.5,"opioidClaims":301,"opioidCost":8001,"opioidBenes":3.0428629195,"opioidRate":3.0428629195,"opioidLAClaims":32,"opioidLARate":10.6,"antibioticClaims":105,"antipsychGE65Claims":79,"avgAge":74.8,"femalePct":58.6,"avgRiskScore":1.38,"riskScore":30,"riskFlags":["high_la_opioid","high_antipsych_elderly"],"riskLevel":"elevated","isExcluded":false,"exclusionInfo":null,"topDrugs":[{"drug":"Apixaban","brand":"Eliquis","claims":101,"cost":105751},{"drug":"Dulaglutide","brand":"Trulicity","claims":54,"cost":85576},{"drug":"Insulin Glargine,hum.Rec.Anlog","brand":"Lantus Solostar","claims":76,"cost":41911},{"drug":"Rivaroxaban","brand":"Xarelto","claims":30,"cost":33034},{"drug":"Mirabegron","brand":"Myrbetriq","claims":23,"cost":31300},{"drug":"Insulin Aspart","brand":"Novolog Flexpen","claims":22,"cost":25586},{"drug":"Insulin Glargine,hum.Rec.Anlog","brand":"Toujeo Solostar","claims":34,"cost":25100},{"drug":"Insulin Aspart","brand":"Novolog","claims":38,"cost":24927},{"drug":"Insulin Glargine,hum.Rec.Anlog","brand":"Basaglar Kwikpen U-100","claims":29,"cost":24074},{"drug":"Empagliflozin","brand":"Jardiance","claims":19,"cost":19777},{"drug":"Fluticasone/Umeclidin/Vilanter","brand":"Trelegy Ellipta","claims":21,"cost":19564},{"drug":"Semaglutide","brand":"Ozempic","claims":18,"cost":17831},{"drug":"Insulin Degludec","brand":"Tresiba Flextouch U-200","claims":11,"cost":14897},{"drug":"Insulin Lispro","brand":"Humalog Kwikpen U-100","claims":15,"cost":14824},{"drug":"Semaglutide","brand":"Rybelsus","claims":15,"cost":13757}]}