{"npi":"1104269836","name":"Valerie Devanney","credentials":"M.D.","entityCode":"I","city":"Wheat Ridge","state":"CO","zip5":"80033","specialty":"Internal Medicine","claims":186,"fills30":247.13,"cost":7070,"daySupply":6580,"benes":28,"costPerBene":252,"costPerClaim":38,"brandClaims":0,"brandCost":0,"genericClaims":168,"genericCost":3965,"brandPct":0,"opioidClaims":64,"opioidCost":2522,"opioidBenes":34.408602151,"opioidRate":34.4,"opioidLAClaims":24,"opioidLARate":37.5,"antibioticClaims":0,"antipsychGE65Claims":0,"avgAge":76.4,"femalePct":57.1,"avgRiskScore":3.14,"riskScore":36,"riskLevel":"elevated","riskFlags":["extreme_opioid_vs_peers","90th_pctile_opioid","high_la_opioid_vs_peers"],"riskComponents":{"opioidPeer":25,"opioidPop":3,"costOutlier":0,"brandPref":0,"opioidLA":8,"antipsych":0,"drugCombo":0,"leie":0,"lowDiversity":0,"frequentFills":0},"zScores":{"opioid":7.03,"cost":-0.25,"brand":-0.78,"opioidLA":5.58},"anomalyScore":36,"isExcluded":false,"exclusionInfo":null,"opioidBenzoCombination":false,"peerComparison":{"opioidVsPeer":1437,"costVsPeer":-82,"brandVsPeer":null},"specialtyAvg":{"opioidRate":2.24,"costPerBene":1411,"brandPct":10.63,"providers":110156},"claimsPerBene":6.64}