{"npi":"1104912476","name":"John Balmer","credentials":"D.O.","entityCode":"I","city":"Spartansburg","state":"PA","zip5":"16434","specialty":"Family Practice","claims":9984,"fills30":15246.6,"cost":1941443,"daySupply":430328,"benes":502,"costPerBene":3867,"costPerClaim":194,"brandClaims":1412,"brandCost":1640516,"genericClaims":8520,"genericCost":298401,"brandPct":14.2,"opioidClaims":1429,"opioidCost":249398,"opioidBenes":14.312900641,"opioidRate":14.3,"opioidLAClaims":479,"opioidLARate":33.5,"antibioticClaims":206,"antipsychGE65Claims":95,"avgAge":67.4,"femalePct":53.2,"avgRiskScore":1.29,"riskScore":45,"riskFlags":["high_opioid_vs_peers","high_la_opioid_vs_peers","high_antipsych_elderly","opioid_benzo_coprescriber","high_fills_per_patient"],"riskLevel":"elevated","isExcluded":false,"exclusionInfo":null,"topDrugs":[{"drug":"Alpha-1-Proteinase Inhibitor","brand":"Glassia","claims":26,"cost":381562},{"drug":"Alpha-1-Proteinase Inhibitor","brand":"Prolastin C","claims":13,"cost":230517},{"drug":"Dulaglutide","brand":"Trulicity","claims":62,"cost":78330},{"drug":"Apixaban","brand":"Eliquis","claims":98,"cost":75582},{"drug":"Empagliflozin","brand":"Jardiance","claims":69,"cost":71660},{"drug":"Oxycodone Hcl","brand":"Oxycontin","claims":45,"cost":71617},{"drug":"Fluticasone/Umeclidin/Vilanter","brand":"Trelegy Ellipta","claims":99,"cost":69488},{"drug":"Semaglutide","brand":"Ozempic","claims":46,"cost":52446},{"drug":"Oxycodone Myristate","brand":"Xtampza Er","claims":13,"cost":46181},{"drug":"Tirzepatide","brand":"Mounjaro","claims":34,"cost":41580},{"drug":"Hydromorphone Hcl","brand":"Dilaudid","claims":28,"cost":38361},{"drug":"Cariprazine Hcl","brand":"Vraylar","claims":25,"cost":36256},{"drug":"Methylnaltrexone Bromide","brand":"Relistor","claims":12,"cost":30082},{"drug":"Rivaroxaban","brand":"Xarelto","claims":48,"cost":29515},{"drug":"Dapagliflozin Propanediol","brand":"Farxiga","claims":20,"cost":22733}],"zScores":{"opioid":2.62,"cost":1.66,"brand":0.63,"opioidLA":4.21},"anomalyScore":45,"peerComparison":{"opioidVsPeer":455,"costVsPeer":262,"brandVsPeer":58},"specialtyAvg":{"opioidRate":2.58,"costPerBene":1068,"brandPct":9,"providers":106889},"drugDiversity":163,"prescribesOpioid":true,"prescribesBenzo":true,"opioidBenzoCombination":true,"iraDrugCost":199489,"glp1Cost":172356,"riskComponents":{"opioidPeer":10,"opioidPop":0,"costOutlier":0,"brandPref":0,"opioidLA":8,"antipsych":10,"drugCombo":8,"leie":0,"lowDiversity":0,"frequentFills":3},"claimsPerBene":19.89}