{"npi":"1114911773","name":"Cheryl Barnes","credentials":"M.D.","entityCode":"I","city":"Louisville","state":"KY","zip5":"40220","specialty":"General Practice","claims":298,"fills30":818.77,"cost":23095,"daySupply":24373,"benes":24,"costPerBene":962,"costPerClaim":78,"brandClaims":29,"brandCost":15139,"genericClaims":269,"genericCost":7956,"brandPct":9.7,"opioidClaims":0,"opioidCost":0,"opioidBenes":0,"opioidRate":0,"opioidLAClaims":0,"opioidLARate":0,"antibioticClaims":0,"antipsychGE65Claims":0,"avgAge":65.2,"femalePct":null,"avgRiskScore":0.8,"riskScore":100,"riskFlags":["leie_excluded"],"riskLevel":"high","isExcluded":true,"exclusionInfo":{"type":"1128a1","date":"20250320","state":"KY"}}