{"npi":"1114940822","name":"Gerhard Nyase","credentials":"M..D.","entityCode":"I","city":"Albuquerque","state":"NM","zip5":"87107","specialty":"Family Practice","claims":11052,"fills30":24609.61,"cost":905525,"daySupply":720102,"benes":778,"costPerBene":1164,"costPerClaim":82,"brandClaims":1269,"brandCost":695995,"genericClaims":9703,"genericCost":206933,"brandPct":11.6,"opioidClaims":477,"opioidCost":10241,"opioidBenes":4.3159609121,"opioidRate":4.3159609121,"opioidLAClaims":19,"opioidLARate":4,"antibioticClaims":231,"antipsychGE65Claims":0,"avgAge":75.2,"femalePct":50,"avgRiskScore":1.57,"riskScore":0,"riskFlags":[],"riskLevel":"low","isExcluded":false,"exclusionInfo":null}