{"npi":"1134671290","name":"Martin Gomez","credentials":"M.D.","entityCode":"I","city":"Hialeah","state":"FL","zip5":"33016","specialty":"General Practice","claims":30509,"fills30":46963.5,"cost":844286,"daySupply":1366961,"benes":775,"costPerBene":1089,"costPerClaim":28,"brandClaims":1436,"brandCost":333312,"genericClaims":28688,"genericCost":497710,"brandPct":4.8,"opioidClaims":78,"opioidCost":249,"opioidBenes":0.2556622636,"opioidRate":0.2556622636,"opioidLAClaims":0,"opioidLARate":0,"antibioticClaims":444,"antipsychGE65Claims":125,"avgAge":74.6,"femalePct":50.7,"avgRiskScore":2.1,"riskScore":15,"riskFlags":["high_antipsych_elderly"],"riskLevel":"moderate","isExcluded":false,"exclusionInfo":null,"topDrugs":[{"drug":"Dabigatran Etexilate Mesylate","brand":"Dabigatran Etexilate","claims":287,"cost":73765},{"drug":"Insulin Glargine-Yfgn","brand":"Insulin Glargine-Yfgn","claims":323,"cost":60379},{"drug":"Fluticasone Propion/Salmeterol","brand":"Fluticasone-Salmeterol","claims":281,"cost":59230},{"drug":"Sacubitril/Valsartan","brand":"Entresto","claims":57,"cost":36397},{"drug":"Apixaban","brand":"Eliquis","claims":48,"cost":27163},{"drug":"Insulin Aspart","brand":"Insulin Aspart Flexpen","claims":84,"cost":22710},{"drug":"Tadalafil","brand":"Tadalafil","claims":600,"cost":20987},{"drug":"Sitagliptin Phosphate","brand":"Januvia","claims":29,"cost":15372},{"drug":"Rivaroxaban","brand":"Xarelto","claims":29,"cost":15054},{"drug":"Tiotropium Bromide","brand":"Spiriva Respimat","claims":30,"cost":14725},{"drug":"Atorvastatin Calcium","brand":"Atorvastatin Calcium","claims":1385,"cost":14246},{"drug":"Pen Needle, Diabetic","brand":"Ulticare Pen Needle","claims":358,"cost":12653},{"drug":"Levothyroxine Sodium","brand":"Levothyroxine Sodium","claims":578,"cost":12122},{"drug":"Ticagrelor","brand":"Brilinta","claims":27,"cost":11641},{"drug":"Albuterol Sulfate","brand":"Albuterol Sulfate Hfa","claims":246,"cost":11294}],"zScores":{"opioid":-0.29,"cost":-0.02,"brand":-0.38,"claims":2.41,"opioidLA":-0.21},"anomalyScore":24.1,"peerComparison":{"opioidVsPeer":-90,"costVsPeer":-3,"brandVsPeer":-43},"specialtyAvg":{"opioidRate":2.48,"costPerBene":1128,"brandPct":8.41,"providers":7389},"drugDiversity":187,"prescribesOpioid":true,"prescribesBenzo":true,"opioidBenzoCombination":true,"iraDrugCost":119199,"glp1Cost":0}