{"npi":"1134249501","name":"Godfried Arthur","credentials":"MD","entityCode":"I","city":"Nashville","state":"NC","zip5":"27856","specialty":"Family Practice","claims":10937,"fills30":23881.49,"cost":1204287,"daySupply":707526,"benes":582,"costPerBene":2069,"costPerClaim":110,"brandClaims":1218,"brandCost":948632,"genericClaims":9658,"genericCost":251606,"brandPct":11.2,"opioidClaims":899,"opioidCost":41676,"opioidBenes":8.2198043339,"opioidRate":8.2198043339,"opioidLAClaims":36,"opioidLARate":4,"antibioticClaims":82,"antipsychGE65Claims":67,"avgAge":69.4,"femalePct":53.1,"avgRiskScore":1.54,"riskScore":15,"riskFlags":["high_antipsych_elderly"],"riskLevel":"moderate","isExcluded":false,"exclusionInfo":null}