{"npi":"1144317702","name":"Oscar Baez-Soria","credentials":"M.D.","entityCode":"I","city":"Vega Baja","state":"PR","zip5":"693","specialty":"Neurology","claims":9153,"fills30":10212.4,"cost":272912,"daySupply":302652,"benes":994,"costPerBene":275,"costPerClaim":30,"brandClaims":332,"brandCost":82509,"genericClaims":8756,"genericCost":188528,"brandPct":3.7,"opioidClaims":0,"opioidCost":0,"opioidBenes":0,"opioidRate":0,"opioidLAClaims":0,"opioidLARate":0,"antibioticClaims":0,"antipsychGE65Claims":113,"avgAge":74,"femalePct":58.9,"avgRiskScore":2.25,"riskScore":15,"riskFlags":["high_antipsych_elderly"],"riskLevel":"moderate","isExcluded":false,"exclusionInfo":null,"topDrugs":[{"drug":"Rivastigmine","brand":"Rivastigmine","claims":182,"cost":32300},{"drug":"Galantamine Hbr","brand":"Galantamine Er","claims":399,"cost":27964},{"drug":"Memantine Hcl","brand":"Memantine Hcl","claims":1338,"cost":22018},{"drug":"Donepezil Hcl","brand":"Donepezil Hcl","claims":1923,"cost":13406},{"drug":"Rotigotine","brand":"Neupro","claims":13,"cost":12368},{"drug":"Rivastigmine","brand":"Exelon","claims":16,"cost":11213},{"drug":"Levetiracetam","brand":"Keppra","claims":13,"cost":11141},{"drug":"Rasagiline Mesylate","brand":"Rasagiline Mesylate","claims":47,"cost":9974},{"drug":"Diclofenac Potassium","brand":"Diclofenac Potassium","claims":194,"cost":9073},{"drug":"Carbamazepine","brand":"Carbamazepine Er","claims":59,"cost":8916},{"drug":"Gabapentin","brand":"Gabapentin","claims":807,"cost":6323},{"drug":"Phenytoin Sodium Extended","brand":"Dilantin","claims":35,"cost":5984},{"drug":"Carbidopa/Levodopa","brand":"Rytary","claims":12,"cost":5976},{"drug":"Divalproex Sodium","brand":"Depakote","claims":12,"cost":5385},{"drug":"Carbamazepine","brand":"Tegretol","claims":12,"cost":5374}]}