{"npi":"1144397613","name":"Vyacheslav Galibov","credentials":"","entityCode":"I","city":"Rego Park","state":"NY","zip5":"11374","specialty":"Internal Medicine","claims":8587,"fills30":17082.86,"cost":1043756,"daySupply":507492,"benes":356,"costPerBene":2932,"costPerClaim":122,"brandClaims":1231,"brandCost":834330,"genericClaims":6978,"genericCost":198431,"brandPct":15,"opioidClaims":0,"opioidCost":0,"opioidBenes":0,"opioidRate":0,"opioidLAClaims":0,"opioidLARate":0,"antibioticClaims":25,"antipsychGE65Claims":0,"avgAge":70.7,"femalePct":57.3,"avgRiskScore":1.67,"riskScore":0,"riskFlags":[],"riskLevel":"low","isExcluded":false,"exclusionInfo":null}