{"npi":"1174612931","name":"Vuppala Reddy","credentials":"M.D.","entityCode":"I","city":"Terre Haute","state":"IN","zip5":"47807","specialty":"Internal Medicine","claims":36313,"fills30":64456.44,"cost":3779950,"daySupply":1800194,"benes":1390,"costPerBene":2719,"costPerClaim":104,"brandClaims":5438,"brandCost":3068488,"genericClaims":30487,"genericCost":690070,"brandPct":15.1,"opioidClaims":652,"opioidCost":27337,"opioidBenes":1.7955002341,"opioidRate":1.7955002341,"opioidLAClaims":27,"opioidLARate":4.1,"antibioticClaims":1173,"antipsychGE65Claims":166,"avgAge":77,"femalePct":59.6,"avgRiskScore":1.44,"riskScore":24,"riskFlags":["high_antipsych_elderly","opioid_benzo_coprescriber","high_fills_per_patient"],"riskLevel":"moderate","isExcluded":false,"exclusionInfo":null,"topDrugs":[{"drug":"Semaglutide","brand":"Ozempic","claims":498,"cost":613238},{"drug":"Apixaban","brand":"Eliquis","claims":630,"cost":355908},{"drug":"Empagliflozin","brand":"Jardiance","claims":209,"cost":206848},{"drug":"Dapagliflozin Propanediol","brand":"Farxiga","claims":164,"cost":192642},{"drug":"Rivaroxaban","brand":"Xarelto","claims":322,"cost":189710},{"drug":"Mirabegron","brand":"Myrbetriq","claims":249,"cost":123465},{"drug":"Sitagliptin Phos/Metformin Hcl","brand":"Janumet","claims":111,"cost":85725},{"drug":"Tirzepatide","brand":"Mounjaro","claims":73,"cost":82253},{"drug":"Fluticasone/Umeclidin/Vilanter","brand":"Trelegy Ellipta","claims":109,"cost":76002},{"drug":"Insulin Glargine/Lixisenatide","brand":"Soliqua 100-33","claims":60,"cost":61107},{"drug":"Sacubitril/Valsartan","brand":"Entresto","claims":91,"cost":56017},{"drug":"Insulin Degludec","brand":"Tresiba Flextouch U-200","claims":54,"cost":53658},{"drug":"Insulin Lispro","brand":"Humalog Kwikpen U-100","claims":73,"cost":52650},{"drug":"Rifaximin","brand":"Xifaxan","claims":18,"cost":47946},{"drug":"Liraglutide","brand":"Victoza 3-Pak","claims":19,"cost":47520}],"zScores":{"opioid":-0.1,"cost":0.28,"brand":0.33,"opioidLA":0.36},"anomalyScore":24,"peerComparison":{"opioidVsPeer":-20,"costVsPeer":93,"brandVsPeer":42},"specialtyAvg":{"opioidRate":2.24,"costPerBene":1411,"brandPct":10.63,"providers":110156},"drugDiversity":260,"prescribesOpioid":true,"prescribesBenzo":true,"opioidBenzoCombination":true,"iraDrugCost":1064593,"glp1Cost":767294,"riskComponents":{"opioidPeer":0,"opioidPop":0,"costOutlier":0,"brandPref":0,"opioidLA":0,"antipsych":10,"drugCombo":8,"leie":0,"lowDiversity":0,"frequentFills":3},"claimsPerBene":26.12}