{"npi":"1285607705","name":"Matthew D'onofrio","credentials":"MD","entityCode":"I","city":"Greensburg","state":"PA","zip5":"15601","specialty":"Internal Medicine","claims":21407,"fills30":42129.76,"cost":2422062,"daySupply":1203096,"benes":1211,"costPerBene":2000,"costPerClaim":113,"brandClaims":3435,"brandCost":1963667,"genericClaims":17780,"genericCost":447477,"brandPct":16.2,"opioidClaims":371,"opioidCost":6309,"opioidBenes":1.7330779652,"opioidRate":1.7,"opioidLAClaims":27,"opioidLARate":7.3,"antibioticClaims":348,"antipsychGE65Claims":98,"avgAge":76.8,"femalePct":48.5,"avgRiskScore":1.23,"riskScore":21,"riskFlags":["high_antipsych_elderly","opioid_benzo_coprescriber"],"riskLevel":"moderate","isExcluded":false,"exclusionInfo":null,"topDrugs":[{"drug":"Apixaban","brand":"Eliquis","claims":413,"cost":285427},{"drug":"Dulaglutide","brand":"Trulicity","claims":131,"cost":184342},{"drug":"Empagliflozin","brand":"Jardiance","claims":165,"cost":167014},{"drug":"Dapagliflozin Propanediol","brand":"Farxiga","claims":214,"cost":130971},{"drug":"Linagliptin","brand":"Tradjenta","claims":137,"cost":110602},{"drug":"Rivaroxaban","brand":"Xarelto","claims":164,"cost":108355},{"drug":"Semaglutide","brand":"Ozempic","claims":93,"cost":94783},{"drug":"Tolvaptan","brand":"Tolvaptan","claims":12,"cost":94152},{"drug":"Insulin Glargine,hum.Rec.Anlog","brand":"Lantus Solostar","claims":183,"cost":64356},{"drug":"Varicella-Zoster Ge/As01b/Pf","brand":"Shingrix","claims":267,"cost":54782},{"drug":"Mirabegron","brand":"Myrbetriq","claims":61,"cost":39713},{"drug":"Rifaximin","brand":"Xifaxan","claims":19,"cost":39629},{"drug":"Fluticasone/Umeclidin/Vilanter","brand":"Trelegy Ellipta","claims":38,"cost":35956},{"drug":"Fluticasone/Vilanterol","brand":"Breo Ellipta","claims":58,"cost":32480},{"drug":"Evolocumab","brand":"Repatha Sureclick","claims":52,"cost":31799}],"zScores":{"opioid":-0.11,"cost":0.13,"brand":0.41,"opioidLA":0.85},"anomalyScore":21,"peerComparison":{"opioidVsPeer":-23,"costVsPeer":42,"brandVsPeer":52},"specialtyAvg":{"opioidRate":2.24,"costPerBene":1411,"brandPct":10.63,"providers":110156},"drugDiversity":207,"prescribesOpioid":true,"prescribesBenzo":true,"opioidBenzoCombination":true,"iraDrugCost":771769,"glp1Cost":298488,"riskComponents":{"opioidPeer":0,"opioidPop":0,"costOutlier":0,"brandPref":0,"opioidLA":0,"antipsych":10,"drugCombo":8,"leie":0,"lowDiversity":0,"frequentFills":0},"claimsPerBene":17.68}