{"npi":"1417067497","name":"Makoto Saigusa","credentials":"D.M.D, M.D.","entityCode":"I","city":"Tyler","state":"TX","zip5":"75701","specialty":"General Practice","claims":376,"fills30":378,"cost":1762,"daySupply":2145,"benes":191,"costPerBene":9,"costPerClaim":5,"brandClaims":0,"brandCost":0,"genericClaims":376,"genericCost":1762,"brandPct":0,"opioidClaims":159,"opioidCost":875,"opioidBenes":42.287234043,"opioidRate":42.287234043,"opioidLAClaims":0,"opioidLARate":0,"antibioticClaims":212,"antipsychGE65Claims":0,"avgAge":70.8,"femalePct":59.7,"avgRiskScore":1.44,"riskScore":30,"riskLevel":"elevated","riskFlags":["extreme_opioid_vs_peers","90th_pctile_opioid"],"riskComponents":{"opioidPeer":25,"opioidPop":5,"costOutlier":0,"brandPref":0,"opioidLA":0,"antipsych":0,"drugCombo":0,"leie":0},"zScores":{"opioid":5.22,"cost":-0.49,"brand":-0.87,"opioidLA":-0.21},"anomalyScore":30,"isExcluded":false,"exclusionInfo":null,"opioidBenzoCombination":false,"peerComparison":{"opioidVsPeer":1608,"costVsPeer":-99,"brandVsPeer":null},"specialtyAvg":{"opioidRate":2.48,"costPerBene":1128,"brandPct":8.41,"providers":7389}}