{"npi":"1467556738","name":"David Kines","credentials":"RN MSN FNPC","entityCode":"I","city":"Dallas","state":"TX","zip5":"75390","specialty":"Nurse Practitioner","claims":74,"fills30":74,"cost":466,"daySupply":449,"benes":55,"costPerBene":8,"costPerClaim":6,"brandClaims":0,"brandCost":0,"genericClaims":74,"genericCost":466,"brandPct":0,"opioidClaims":46,"opioidCost":189,"opioidBenes":62.162162162,"opioidRate":62.162162162,"opioidLAClaims":0,"opioidLARate":0,"antibioticClaims":15,"antipsychGE65Claims":0,"avgAge":69.5,"femalePct":54.5,"avgRiskScore":1.24,"riskScore":35,"riskLevel":"elevated","riskFlags":["extreme_opioid_vs_peers","95th_pctile_opioid"],"riskComponents":{"opioidPeer":25,"opioidPop":10,"costOutlier":0,"brandPref":0,"opioidLA":0,"antipsych":0,"drugCombo":0,"leie":0},"zScores":{"opioid":5.71,"cost":-0.38,"brand":-0.67,"opioidLA":-0.22},"anomalyScore":35,"isExcluded":false,"exclusionInfo":null,"opioidBenzoCombination":false,"peerComparison":{"opioidVsPeer":1544,"costVsPeer":-99,"brandVsPeer":null},"specialtyAvg":{"opioidRate":3.78,"costPerBene":1174,"brandPct":8.87,"providers":218535}}