{"npi":"1578569786","name":"Karen Donaldson","credentials":"MD","entityCode":"I","city":"Baltimore","state":"MD","zip5":"21213","specialty":"Family Practice","claims":68763,"fills30":68815.04,"cost":17734372,"daySupply":77962,"benes":53065,"costPerBene":334,"costPerClaim":258,"brandClaims":68720,"brandCost":17730919,"genericClaims":0,"genericCost":0,"brandPct":100,"opioidClaims":0,"opioidCost":0,"opioidBenes":0,"opioidRate":0,"opioidLAClaims":0,"opioidLARate":0,"antibioticClaims":0,"antipsychGE65Claims":0,"avgAge":75,"femalePct":59.6,"avgRiskScore":1.01,"riskScore":10,"riskFlags":["extreme_brand"],"riskLevel":"moderate","isExcluded":false,"exclusionInfo":null}