{"npi":"1619354479","name":"Charlene Shuler","credentials":"CNP","entityCode":"I","city":"Marysville","state":"OH","zip5":"43040","specialty":"Nurse Practitioner","claims":3505,"fills30":3661,"cost":104680,"daySupply":99663,"benes":596,"costPerBene":176,"costPerClaim":30,"brandClaims":136,"brandCost":17879,"genericClaims":3369,"genericCost":86801,"brandPct":3.9,"opioidClaims":2469,"opioidCost":76528,"opioidBenes":70.442225392,"opioidRate":70.442225392,"opioidLAClaims":199,"opioidLARate":8.1,"antibioticClaims":0,"antipsychGE65Claims":0,"avgAge":70.1,"femalePct":64.9,"avgRiskScore":1.66,"riskScore":42,"riskLevel":"elevated","riskFlags":["extreme_opioid_vs_peers","99th_pctile_opioid"],"riskComponents":{"opioidPeer":25,"opioidPop":15,"costOutlier":0,"brandPref":0,"opioidLA":0,"antipsych":0,"drugCombo":0,"leie":0,"lowDiversity":0,"frequentFills":0},"zScores":{"opioid":6.52,"cost":-0.33,"brand":-0.37,"opioidLA":1.12},"anomalyScore":42,"isExcluded":false,"exclusionInfo":null,"opioidBenzoCombination":false,"peerComparison":{"opioidVsPeer":1762,"costVsPeer":-85,"brandVsPeer":-56},"specialtyAvg":{"opioidRate":3.78,"costPerBene":1174,"brandPct":8.87,"providers":218535},"claimsPerBene":5.88}