{"npi":"1639130693","name":"Mark Buchfuhrer","credentials":"MD","entityCode":"I","city":"Downey","state":"CA","zip5":"90241","specialty":"Pulmonary Disease","claims":6942,"fills30":11005.76,"cost":2158843,"daySupply":320400,"benes":809,"costPerBene":2669,"costPerClaim":311,"brandClaims":0,"brandCost":0,"genericClaims":4678,"genericCost":219334,"brandPct":0,"opioidClaims":1261,"opioidCost":158151,"opioidBenes":18.164794007,"opioidRate":18.164794007,"opioidLAClaims":811,"opioidLARate":64.3,"antibioticClaims":31,"antipsychGE65Claims":0,"avgAge":74.7,"femalePct":59.7,"avgRiskScore":1.74,"riskScore":38,"riskLevel":"elevated","riskFlags":["extreme_opioid_vs_peers","high_la_opioid_vs_peers"],"riskComponents":{"opioidPeer":25,"opioidPop":0,"costOutlier":0,"brandPref":0,"opioidLA":8,"antipsych":0,"drugCombo":0,"leie":0,"lowDiversity":0,"frequentFills":0},"zScores":{"opioid":9.91,"cost":-0.21,"brand":-1.76,"opioidLA":11.64},"anomalyScore":38,"isExcluded":false,"exclusionInfo":null,"opioidBenzoCombination":false,"peerComparison":{"opioidVsPeer":null,"costVsPeer":-48,"brandVsPeer":null},"specialtyAvg":{"opioidRate":0.21,"costPerBene":5138,"brandPct":61.36,"providers":9082},"claimsPerBene":8.58}