{"npi":"1649247545","name":"Igor Bidikov","credentials":"MD","entityCode":"I","city":"Heflin","state":"AL","zip5":"36264","specialty":"Internal Medicine","claims":26242,"fills30":38000.25,"cost":1911671,"daySupply":1056619,"benes":1099,"costPerBene":1739,"costPerClaim":73,"brandClaims":3112,"brandCost":1396665,"genericClaims":22992,"genericCost":503150,"brandPct":11.9,"opioidClaims":2362,"opioidCost":66219,"opioidBenes":9.0008383507,"opioidRate":9.0008383507,"opioidLAClaims":150,"opioidLARate":6.4,"antibioticClaims":886,"antipsychGE65Claims":416,"avgAge":72.1,"femalePct":64.4,"avgRiskScore":1.82,"riskScore":12,"riskFlags":["high_antipsych_elderly"],"riskLevel":"low","isExcluded":false,"exclusionInfo":null,"zScores":{"opioid":1.48,"cost":0.07,"brand":0.09,"opioidLA":0.71},"anomalyScore":12,"peerComparison":{"opioidVsPeer":302,"costVsPeer":23,"brandVsPeer":12},"specialtyAvg":{"opioidRate":2.24,"costPerBene":1411,"brandPct":10.63,"providers":110156},"riskComponents":{"opioidPeer":0,"opioidPop":0,"costOutlier":0,"brandPref":0,"opioidLA":0,"antipsych":10,"drugCombo":0,"leie":0}}