{"npi":"1699945808","name":"Kathleen Ragen","credentials":"MD","entityCode":"I","city":"Minneapolis","state":"MN","zip5":"55407","specialty":"Family Practice","claims":832,"fills30":961.68,"cost":40158,"daySupply":23586,"benes":125,"costPerBene":321,"costPerClaim":48,"brandClaims":57,"brandCost":12469,"genericClaims":775,"genericCost":27689,"brandPct":6.9,"opioidClaims":444,"opioidCost":26223,"opioidBenes":53.365384615,"opioidRate":53.365384615,"opioidLAClaims":171,"opioidLARate":38.5,"antibioticClaims":0,"antipsychGE65Claims":15,"avgAge":70.3,"femalePct":52.8,"avgRiskScore":3.23,"riskScore":43,"riskLevel":"elevated","riskFlags":["extreme_opioid_vs_peers","95th_pctile_opioid","high_la_opioid_vs_peers"],"riskComponents":{"opioidPeer":25,"opioidPop":10,"costOutlier":0,"brandPref":0,"opioidLA":8,"antipsych":0,"drugCombo":0,"leie":0},"zScores":{"opioid":11.34,"cost":-0.44,"brand":-0.26,"opioidLA":4.89},"anomalyScore":43,"isExcluded":false,"exclusionInfo":null,"opioidBenzoCombination":false,"peerComparison":{"opioidVsPeer":1969,"costVsPeer":-70,"brandVsPeer":-24},"specialtyAvg":{"opioidRate":2.58,"costPerBene":1068,"brandPct":9,"providers":106889}}