{"npi":"1720550809","name":"Nicole Smith","credentials":"FNP-C","entityCode":"I","city":"Phoenix","state":"AZ","zip5":"85016","specialty":"Nurse Practitioner","claims":612,"fills30":675,"cost":25400,"daySupply":18124,"benes":232,"costPerBene":109,"costPerClaim":42,"brandClaims":25,"brandCost":10881,"genericClaims":587,"genericCost":14519,"brandPct":4.1,"opioidClaims":432,"opioidCost":20924,"opioidBenes":70.588235294,"opioidRate":70.588235294,"opioidLAClaims":77,"opioidLARate":17.8,"antibioticClaims":0,"antipsychGE65Claims":0,"avgAge":74.3,"femalePct":70.7,"avgRiskScore":1.58,"riskScore":44,"riskLevel":"elevated","riskFlags":["extreme_opioid_vs_peers","99th_pctile_opioid","elevated_la_opioid"],"riskComponents":{"opioidPeer":25,"opioidPop":15,"costOutlier":0,"brandPref":0,"opioidLA":4,"antipsych":0,"drugCombo":0,"leie":0,"lowDiversity":0,"frequentFills":0},"zScores":{"opioid":6.53,"cost":-0.35,"brand":-0.36,"opioidLA":2.74},"anomalyScore":44,"isExcluded":false,"exclusionInfo":null,"opioidBenzoCombination":false,"peerComparison":{"opioidVsPeer":1766,"costVsPeer":-91,"brandVsPeer":-54},"specialtyAvg":{"opioidRate":3.78,"costPerBene":1174,"brandPct":8.87,"providers":218535},"claimsPerBene":2.64}