{"npi":"1720215023","name":"Rebecca Schrader","credentials":"FNP","entityCode":"I","city":"Lafayette","state":"IN","zip5":"47904","specialty":"Nurse Practitioner","claims":424,"fills30":426.8,"cost":7966,"daySupply":3989,"benes":190,"costPerBene":42,"costPerClaim":19,"brandClaims":15,"brandCost":3195,"genericClaims":409,"genericCost":4770,"brandPct":3.5,"opioidClaims":268,"opioidCost":3408,"opioidBenes":63.20754717,"opioidRate":63.20754717,"opioidLAClaims":0,"opioidLARate":0,"antibioticClaims":45,"antipsychGE65Claims":0,"avgAge":72.4,"femalePct":64.2,"avgRiskScore":0.98,"riskScore":35,"riskLevel":"elevated","riskFlags":["extreme_opioid_vs_peers","95th_pctile_opioid"],"riskComponents":{"opioidPeer":25,"opioidPop":10,"costOutlier":0,"brandPref":0,"opioidLA":0,"antipsych":0,"drugCombo":0,"leie":0,"lowDiversity":0,"frequentFills":0},"zScores":{"opioid":5.81,"cost":-0.37,"brand":-0.4,"opioidLA":-0.22},"anomalyScore":35,"isExcluded":false,"exclusionInfo":null,"opioidBenzoCombination":false,"peerComparison":{"opioidVsPeer":1571,"costVsPeer":-96,"brandVsPeer":-60},"specialtyAvg":{"opioidRate":3.78,"costPerBene":1174,"brandPct":8.87,"providers":218535},"claimsPerBene":2.23}