{"npi":"1740387646","name":"Dong Shin","credentials":"M.D.","entityCode":"I","city":"Los Angeles","state":"CA","zip5":"90006","specialty":"Internal Medicine","claims":41985,"fills30":48167.27,"cost":7531537,"daySupply":1351135,"benes":687,"costPerBene":10963,"costPerClaim":179,"brandClaims":11102,"brandCost":6529837,"genericClaims":30638,"genericCost":996752,"brandPct":26.6,"opioidClaims":571,"opioidCost":7917,"opioidBenes":1.3600095272,"opioidRate":1.3600095272,"opioidLAClaims":0,"opioidLARate":0,"antibioticClaims":620,"antipsychGE65Claims":257,"avgAge":80.1,"femalePct":63,"avgRiskScore":1.94,"riskScore":23,"riskFlags":["high_cost","high_antipsych_elderly"],"riskLevel":"moderate","isExcluded":false,"exclusionInfo":null,"zScores":{"opioid":-0.19,"cost":2.03,"brand":1.17,"claims":6.18,"opioidLA":-0.29},"anomalyScore":119.9,"peerComparison":{"opioidVsPeer":-39,"costVsPeer":677,"brandVsPeer":150},"specialtyAvg":{"opioidRate":2.24,"costPerBene":1411,"brandPct":10.63,"providers":110156}}