{"npi":"1780665828","name":"Jefferey Adair","credentials":"MD","entityCode":"I","city":"Shreveport","state":"LA","zip5":"71105","specialty":"Interventional Pain Management","claims":15540,"fills30":16959.32,"cost":865665,"daySupply":490465,"benes":1478,"costPerBene":586,"costPerClaim":56,"brandClaims":0,"brandCost":0,"genericClaims":14753,"genericCost":389359,"brandPct":0,"opioidClaims":10134,"opioidCost":591761,"opioidBenes":1317,"opioidRate":65.212355212,"opioidLAClaims":1198,"opioidLARate":11.8,"antibioticClaims":22,"antipsychGE65Claims":0,"avgAge":65.7,"femalePct":60.1,"avgRiskScore":1.47,"riskScore":50,"riskFlags":["very_high_opioid","high_la_opioid","high_volume_opioid"],"riskLevel":"high","isExcluded":false,"exclusionInfo":null}