{"npi":"1821253162","name":"Scotty Ortega","credentials":"M.D.","entityCode":"I","city":"Odessa","state":"TX","zip5":"79761","specialty":"Family Practice","claims":56442,"fills30":64531.5,"cost":4151972,"daySupply":1553019,"benes":1468,"costPerBene":2828,"costPerClaim":74,"brandClaims":6902,"brandCost":3065586,"genericClaims":49049,"genericCost":1042629,"brandPct":12.3,"opioidClaims":1863,"opioidCost":45035,"opioidBenes":3.3007334963,"opioidRate":3.3007334963,"opioidLAClaims":22,"opioidLARate":1.2,"antibioticClaims":1445,"antipsychGE65Claims":970,"avgAge":75.2,"femalePct":60.1,"avgRiskScore":2.2,"riskScore":15,"riskFlags":["high_antipsych_elderly"],"riskLevel":"moderate","isExcluded":false,"exclusionInfo":null}