{"npi":"1902875552","name":"Yao Huang","credentials":"MD","entityCode":"I","city":"Wichita Falls","state":"TX","zip5":"76301","specialty":"Family Practice","claims":20976,"fills30":33435.45,"cost":2414441,"daySupply":970088,"benes":711,"costPerBene":3396,"costPerClaim":115,"brandClaims":2638,"brandCost":2085158,"genericClaims":18140,"genericCost":312168,"brandPct":12.7,"opioidClaims":739,"opioidCost":14576,"opioidBenes":3.5230739893,"opioidRate":3.5230739893,"opioidLAClaims":0,"opioidLARate":0,"antibioticClaims":453,"antipsychGE65Claims":108,"avgAge":67.3,"femalePct":49.2,"avgRiskScore":1.56,"riskScore":15,"riskFlags":["high_antipsych_elderly"],"riskLevel":"moderate","isExcluded":false,"exclusionInfo":null,"zScores":{"opioid":0.21,"cost":1.38,"brand":0.45,"claims":2.46,"opioidLA":-0.35},"anomalyScore":64.3,"peerComparison":{"opioidVsPeer":37,"costVsPeer":218,"brandVsPeer":41},"specialtyAvg":{"opioidRate":2.58,"costPerBene":1068,"brandPct":9,"providers":106889}}