{"npi":"1962406793","name":"Richard Clark","credentials":"MD","entityCode":"I","city":"Jamestown","state":"TN","zip5":"38556","specialty":"Internal Medicine","claims":9852,"fills30":11435.92,"cost":694405,"daySupply":329628,"benes":516,"costPerBene":1346,"costPerClaim":70,"brandClaims":965,"brandCost":439226,"genericClaims":8869,"genericCost":254300,"brandPct":9.8,"opioidClaims":4006,"opioidCost":207368,"opioidBenes":40.661794559,"opioidRate":40.7,"opioidLAClaims":481,"opioidLARate":12,"antibioticClaims":110,"antipsychGE65Claims":22,"avgAge":67.7,"femalePct":56.8,"avgRiskScore":1.71,"riskScore":44,"riskLevel":"elevated","riskFlags":["extreme_opioid_vs_peers","90th_pctile_opioid","elevated_antipsych_elderly","high_fills_per_patient"],"riskComponents":{"opioidPeer":25,"opioidPop":5,"costOutlier":0,"brandPref":0,"opioidLA":0,"antipsych":5,"drugCombo":0,"leie":0,"lowDiversity":0,"frequentFills":3},"zScores":{"opioid":8.4,"cost":-0.01,"brand":-0.06,"opioidLA":1.59},"anomalyScore":44,"isExcluded":false,"exclusionInfo":null,"opioidBenzoCombination":false,"peerComparison":{"opioidVsPeer":1717,"costVsPeer":-5,"brandVsPeer":-8},"specialtyAvg":{"opioidRate":2.24,"costPerBene":1411,"brandPct":10.63,"providers":110156},"claimsPerBene":19.09}