{"npi":"1992739734","name":"R. Murphy","credentials":"D.D.S., M.D.","entityCode":"I","city":"Huntington","state":"WV","zip5":"25702","specialty":"Oral Surgery (Dentist only)","claims":125,"fills30":125,"cost":1222,"daySupply":713,"benes":92,"costPerBene":13,"costPerClaim":10,"brandClaims":0,"brandCost":0,"genericClaims":125,"genericCost":1222,"brandPct":0,"opioidClaims":102,"opioidCost":1126,"opioidBenes":81.6,"opioidRate":81.6,"opioidLAClaims":0,"opioidLARate":0,"antibioticClaims":21,"antipsychGE65Claims":0,"avgAge":67.1,"femalePct":51.1,"avgRiskScore":1.06,"riskScore":27,"riskLevel":"moderate","riskFlags":["very_high_opioid_vs_peers","99th_pctile_opioid"],"riskComponents":{"opioidPeer":18,"opioidPop":9,"costOutlier":0,"brandPref":0,"opioidLA":0,"antipsych":0,"drugCombo":0,"leie":0,"lowDiversity":0,"frequentFills":0},"zScores":{"opioid":4.27,"cost":-0.08,"brand":-0.08,"opioidLA":-0.03},"anomalyScore":27,"isExcluded":false,"exclusionInfo":null,"opioidBenzoCombination":false,"peerComparison":{"opioidVsPeer":296,"costVsPeer":null,"brandVsPeer":null},"specialtyAvg":{"opioidRate":20.61,"costPerBene":20,"brandPct":0.1,"providers":5119},"claimsPerBene":1.36}