{"city":"Greeneville","state":"TN","slug":"greeneville-tn","providers":5,"totalCost":6167341,"totalClaims":69896,"highRisk":0,"elevated":0,"specialties":3,"avgOpioidRate":3.33,"topProviders":[{"npi":"1760775365","name":"Valerie Mullins","specialty":"Physician Assistant","cost":2737249,"claims":24763,"riskLevel":"moderate","opioidRate":2.9964059282},{"npi":"1073874277","name":"Ann Espey","specialty":"Nurse Practitioner","cost":1012760,"claims":8969,"riskLevel":"low","opioidRate":0.5463262348},{"npi":"1013966886","name":"Jaime Oakley","specialty":"Family Practice","cost":822522,"claims":11747,"riskLevel":"moderate","opioidRate":5.0821486337},{"npi":"1104853639","name":"Sonja Woods","specialty":"Family Practice","cost":822409,"claims":8672,"riskLevel":"low","opioidRate":4.2089483395},{"npi":"1013900943","name":"Andy Roberts","specialty":"Family Practice","cost":772401,"claims":15745,"riskLevel":"low","opioidRate":3.8234360114}]}